redis_wrapper/__init__.py
redis_wrapper/cache_manager.py
redis_wrapper-0.1.1.dist-info/LICENSE
redis_wrapper-0.1.1.dist-info/METADATA
redis_wrapper-0.1.1.dist-info/WHEEL
redis_wrapper-0.1.1.dist-info/top_level.txt
redis_wrapper-0.1.1.dist-info/RECORD
