Metadata-Version: 2.1
Name: redis-wrapper
Version: 0.1.1
Summary: wrapper for redis connection, implements reading, writing, subscribing channels and listening channels
Home-page: UNKNOWN
Author: Roy Hayumi
Author-email: roy.hayumi@gmail.com
License: UNKNOWN
Platform: UNKNOWN
Classifier: Programming Language :: Python :: 3
Classifier: License :: OSI Approved :: MIT License
Classifier: Operating System :: OS Independent
Requires-Python: >=3.6
License-File: LICENSE
Requires-Dist: redis (==3.4.1)
